<?xml version="1.0" encoding="UTF-8"?>
<MetaDataObject xmlns="http://v8.1c.ru/8.3/MDClasses" xmlns:app="http://v8.1c.ru/8.2/managed-application/core" xmlns:cfg="http://v8.1c.ru/8.1/data/enterprise/current-config" xmlns:cmi="http://v8.1c.ru/8.2/managed-application/cmi" xmlns:ent="http://v8.1c.ru/8.1/data/enterprise" xmlns:lf="http://v8.1c.ru/8.2/managed-application/logform" xmlns:style="http://v8.1c.ru/8.1/data/ui/style" xmlns:sys="http://v8.1c.ru/8.1/data/ui/fonts/system" xmlns:v8="http://v8.1c.ru/8.1/data/core" xmlns:v8ui="http://v8.1c.ru/8.1/data/ui" xmlns:web="http://v8.1c.ru/8.1/data/ui/colors/web" xmlns:win="http://v8.1c.ru/8.1/data/ui/colors/windows" xmlns:xen="http://v8.1c.ru/8.3/xcf/enums" xmlns:xpr="http://v8.1c.ru/8.3/xcf/predef" xmlns:xr="http://v8.1c.ru/8.3/xcf/readable" xmlns:xs="http://www.w3.org/2001/XMLSchema" xmlns:xsi="http://www.w3.org/2001/XMLSchema-instance" version="2.3">
	<Constant uuid="7584857d-d052-4d16-9240-3d259e15ce38">
		<InternalInfo>
			<xr:GeneratedType name="ConstantManager.ВестиУчетМаркировкиПродукцииВГИСМ" category="Manager">
				<xr:TypeId>5f032f3d-3a26-4781-8a3f-6cab647d1023</xr:TypeId>
				<xr:ValueId>60e26da2-cb3b-407e-b5ca-7cacb710fbdc</xr:ValueId>
			</xr:GeneratedType>
			<xr:GeneratedType name="ConstantValueManager.ВестиУчетМаркировкиПродукцииВГИСМ" category="ValueManager">
				<xr:TypeId>19aca225-117d-4f9e-990b-b0ad91b1202e</xr:TypeId>
				<xr:ValueId>be515d79-33df-4bd7-b2e6-3a73b6ad263b</xr:ValueId>
			</xr:GeneratedType>
		</InternalInfo>
		<Properties>
			<Name>ВестиУчетМаркировкиПродукцииВГИСМ</Name>
			<ObjectBelonging>Adopted</ObjectBelonging>
			<Type>
				<v8:Type>xs:boolean</v8:Type>
			</Type>
		</Properties>
	</Constant>
</MetaDataObject>